{
  "contacts": [
    {
      "firstName": "Sebastian",
      "lastName": "Kreft",
      "phoneNumber": "500-600-700",
      "email": "seba@mail.com",
      "id": 1
    },
    {
      "firstName": "Maciej",
      "lastName": "Arendt",
      "phoneNumber": "600500500",
      "email": "email@gmail.com",
      "id": 4
    },
    {
      "firstName": "Jan",
      "lastName": "Kowalski",
      "phoneNumber": "500500500",
      "email": "e-mail@gmail.com",
      "id": 6
    },
    {
      "firstName": "Anna",
      "lastName": "Nowak",
      "phoneNumber": "700800900",
      "email": "ema@wp.pl",
      "id": 7
    }
  ]
}